swarmauri_keyprovider_gcpkms/GcpKmsKeyProvider.py
swarmauri_keyprovider_gcpkms/__init__.py
swarmauri_keyprovider_gcpkms-0.9.0.dev4.dist-info/LICENSE
swarmauri_keyprovider_gcpkms-0.9.0.dev4.dist-info/METADATA
swarmauri_keyprovider_gcpkms-0.9.0.dev4.dist-info/WHEEL
swarmauri_keyprovider_gcpkms-0.9.0.dev4.dist-info/entry_points.txt
swarmauri_keyprovider_gcpkms-0.9.0.dev4.dist-info/RECORD
