Metadata-Version: 2.3
Name: swarmauri_keyprovider_gcpkms
Version: 0.9.0.dev4
Summary: Google Cloud KMS Key Provider for Swarmauri
License: Apache-2.0
Author: Swarmauri
Author-email: opensource@swarmauri.com
Requires-Python: >=3.10,<3.13
Classifier: License :: OSI Approved :: Apache Software License
Classifier: Programming Language :: Python :: 3.10
Classifier: Programming Language :: Python :: 3.11
Classifier: Programming Language :: Python :: 3.12
Provides-Extra: cbor
Requires-Dist: cbor2 ; extra == "cbor"
Requires-Dist: cryptography
Requires-Dist: google-auth
Requires-Dist: requests
Requires-Dist: swarmauri_base
Requires-Dist: swarmauri_core
Requires-Dist: swarmauri_standard
